qualesim_tequila/__init__.py
qualesim_tequila/__main__.py
qualesim_tequila/backend.py
qualesim_tequila/test.py
qualesim_tequila-1.0.3.data/data/bin/dqcsbetequila
qualesim_tequila-1.0.3.dist-info/METADATA
qualesim_tequila-1.0.3.dist-info/WHEEL
qualesim_tequila-1.0.3.dist-info/top_level.txt
qualesim_tequila-1.0.3.dist-info/RECORD
