Metadata-Version: 2.1
Name: qualesim-tequila
Version: 1.0.3
Summary: DQCsim backend for tequila.
Home-page: https://gitee.com/hpcl_quanta/dqcsim-tequila.git
Author: Dingdong Liu
Author-email: dingdongliu@quanta.org.cn
License: GPLv3
Keywords: qualesim tequila
Classifier: Development Status :: 3 - Alpha
Classifier: Intended Audience :: Science/Research
Classifier: License :: OSI Approved :: GNU General Public License v3 (GPLv3)
Classifier: Topic :: Scientific/Engineering
